{
    "id": 10007973,
    "title": "勇闯原始森林！挑战贝爷！...额还是算了吧Marina Beach Park Edmonds",
    "abstract": "额看视频吧！！！",
    "authorId": 35457892,
    "uploadTime": 1492832528.0,
    "playCount": 177,
    "commentCount": 6,
    "bulletCommentCount": 3,
    "imageUrl": "http://i1.hdslb.com/bfs/archive/eb96a3763cac54f1108883ebd1b8873034db45db.jpg",
    "feedback": {
        "like": "0",
        "coin": "8",
        "star": "0",
        "share": "71"
    },
    "comments": [
        "知名偶像",
        "见习搬运工",
        "收集萌新",
        "饭圈楷模",
        "学生卡"
    ],
    "tags": [
        "美国",
        "摄影",
        "生活",
        "日常",
        "自然",
        "日常",
        "自制",
        "贝爷生存"
    ]
}