{
    "id": 1005873,
    "title": "【默寒】我的模拟人生  实况流程 Part2",
    "abstract": "自制 哈喽！游戏大丈夫-我的模拟人生，不一样的模拟人生，是不是很可爱呢？粉丝交流群：288099328极游网YY频道：30365；请大家多多关注黙寒ZT吧！",
    "authorId": 1323620,
    "uploadTime": 1394578961.0,
    "playCount": 777,
    "commentCount": 2,
    "bulletCommentCount": 27,
    "imageUrl": "http://i0.hdslb.com/bfs/archive/f574828a6c437eede5423abe659db336489a7d20.jpg",
    "feedback": {
        "like": "0",
        "coin": "2",
        "star": "2",
        "share": "2"
    },
    "comments": [
        "好人卡",
        "好人卡"
    ],
    "tags": [
        "利威尔",
        "模拟人生",
        "游戏",
        "单机游戏",
        "实况攻略",
        "一米六",
        "默寒",
        "原创",
        "实况解说",
        "萌世界",
        "我的模拟人生",
        "游戏大丈夫",
        "兵长",
        "MYSIMS"
    ]
}