{
    "id": 20003330,
    "title": "20171119 S队MC1火锅必吃/公司行程太累感想剪辑 孙芮钱蓓婷莫寒张语格陈观慧等 SNH48公演",
    "abstract": "20171119 S队MC1火锅必吃的东西/公司行程太累敢想剪辑 陈观慧张语格有共同语言莫寒受干扰 孙芮钱蓓婷徐子轩袁丹妮温晶婕陈思蒋芸等 SNH48公演",
    "authorId": 8522986,
    "uploadTime": 1519473472.0,
    "playCount": 10181,
    "commentCount": 27,
    "bulletCommentCount": 142,
    "imageUrl": "http://i2.hdslb.com/bfs/archive/4289c054e3a9441b92ce8e30d8d3d5fbb013a335.jpg",
    "feedback": {
        "like": "155",
        "coin": "17",
        "star": "189",
        "share": "16"
    },
    "comments": [
        "防火，防盗，防络毛",
        "饭圈萌新",
        "饭圈萌新",
        "络络:防我？防不住的",
        "饭圈楷模"
    ],
    "tags": [
        "徐子轩",
        "钱蓓婷",
        "张语格",
        "莫寒",
        "孙芮",
        "SNH48",
        "娱乐",
        "明星",
        "明星",
        "陈观慧",
        "温晶婕",
        "袁丹妮",
        "S队"
    ]
}