{
    "id": 20003411,
    "title": "玩足狗年群星夢幻戰-HANA菊梓喬 2018-02-16",
    "abstract": "玩足狗年群星夢幻戰-HANA菊梓喬 2018-02-16",
    "authorId": 10943657,
    "uploadTime": 1519478726.0,
    "playCount": 186,
    "commentCount": 0,
    "bulletCommentCount": 0,
    "imageUrl": "http://i1.hdslb.com/bfs/archive/28654b43836a074b52229ff8233fea971630e0dd.jpg",
    "feedback": {
        "like": "3",
        "coin": "0",
        "star": "4",
        "share": "5"
    },
    "comments": [],
    "tags": [
        "娱乐",
        "综艺",
        "綜藝"
    ]
}