{
    "id": 30007469,
    "title": "艺兴，你的星矢来了",
    "abstract": "-",
    "authorId": 122401455,
    "uploadTime": 1534915956.0,
    "playCount": 69,
    "commentCount": 3,
    "bulletCommentCount": 0,
    "imageUrl": "http://i2.hdslb.com/bfs/archive/a7da9cacdfbc6d102b41c62a06599fbe7225b0ad.jpg",
    "feedback": {
        "like": "4",
        "coin": "4",
        "star": "1",
        "share": "5"
    },
    "comments": [
        "饭圈楷模",
        "收集萌新",
        "收集萌新"
    ],
    "tags": [
        "据说以前不叫兴迷，兴使，兴奋了解一下"
    ]
}