{
    "id": 3005668,
    "title": "月刊VOCALOD TOP30 2015年10月号",
    "abstract": "sm27296509 集計期間:9月1日5時～10月1日5時\n前月号：sm27076821",
    "authorId": 797614,
    "uploadTime": 1443961467.0,
    "playCount": 508,
    "commentCount": 12,
    "bulletCommentCount": 54,
    "imageUrl": "http://i2.hdslb.com/bfs/archive/d80c816f7e660f530f1181eabd3af9edd09da737.jpg",
    "feedback": {
        "like": "1",
        "coin": "0",
        "star": "10",
        "share": "1"
    },
    "comments": [
        "高级搬运工",
        "见习偶像",
        "收集萌新",
        "青铜殿堂",
        "人理拯救者"
    ],
    "tags": [
        "VOCALOID",
        "虚拟歌手",
        "音乐",
        "VOCALOID·UTAU",
        "月刊VOCALOID"
    ]
}