{
    "id": 3005832,
    "title": "【SNH48】[龚诗淇]热带雨林",
    "abstract": "自制 十七和她喜欢的前辈樱花花",
    "authorId": 12718071,
    "uploadTime": 1443962888.0,
    "playCount": 404,
    "commentCount": 1,
    "bulletCommentCount": 3,
    "imageUrl": "http://i2.hdslb.com/bfs/archive/1a23ffc054e4da613b9b1a374c47fcd40f0f7f51.png",
    "feedback": {
        "like": "0",
        "coin": "0",
        "star": "2",
        "share": "7"
    },
    "comments": [
        "青铜殿堂"
    ],
    "tags": [
        "SNH48",
        "娱乐",
        "明星",
        "明星",
        "塞纳河",
        "龚诗淇",
        "生男孩"
    ]
}