{
    "id": 3005549,
    "title": "【食嫌】150806 哈梅斯VS泷川雅美【中字自制】",
    "abstract": " 中字自制\n\n2015年8月6日 哈梅斯•演技为负•死不认输•我不管你骗人•罗德里格斯和泷川雅美的食嫌王大对决！\n\n",
    "authorId": 2961670,
    "uploadTime": 1443960349.0,
    "playCount": 5644,
    "commentCount": 11,
    "bulletCommentCount": 319,
    "imageUrl": "http://i0.hdslb.com/bfs/archive/b5461304ce4054a9b11f86de88705dae5e4cdd9c.jpg",
    "feedback": {
        "like": "8",
        "coin": "20",
        "star": "153",
        "share": "31"
    },
    "comments": [
        "哈妹太可爱了哈哈哈",
        "(｀・ω・´)哈妹太萌了！！！！啊啊啊一直在笑太可爱了！！",
        "知名偶像",
        "简直太好骗了",
        "啊啊啊啊啊啊啊啊啊小哈太可爱呀～"
    ],
    "tags": [
        "综艺",
        "娱乐",
        "综艺",
        "食嫌王",
        "皇家马德里",
        "J罗",
        "泷川雅美",
        "哈梅斯罗德里格斯"
    ]
}