{
    "id": 3005782,
    "title": "Funky Style By DJ mr.xuan",
    "abstract": "转载自优酷网mr.宣的作品，这是我个人第一个上传的视频。好吧虽然没图像的说……",
    "authorId": 4188868,
    "uploadTime": 1443962504.0,
    "playCount": 180,
    "commentCount": 8,
    "bulletCommentCount": 4,
    "imageUrl": "http://i0.hdslb.com/bfs/archive/72b82f5fccf5a7e47e959063f7e9f81d4c0eb3cb.jpg",
    "feedback": {
        "like": "0",
        "coin": "1",
        "star": "4",
        "share": "1"
    },
    "comments": [
        "大会员2018年度勋章",
        "青铜殿堂",
        "大会员2018年度勋章",
        "我也是追了",
        "大会员2018年度勋章"
    ],
    "tags": [
        "音乐",
        "音乐综合",
        "作业用",
        "REMIX",
        "音乐",
        "音乐视频"
    ]
}