{
    "id": 3006074,
    "title": " 【9muses】9muses  Hurt Locker 后台花絮合辑 英字",
    "abstract": "Youtube  N87 Nine Muses  Hurt Locker Music Core Backstage",
    "authorId": 3867829,
    "uploadTime": 1443964865.0,
    "playCount": 846,
    "commentCount": 3,
    "bulletCommentCount": 11,
    "imageUrl": "http://i1.hdslb.com/bfs/archive/8fc5eb8946a39536843a38aa66655440f158318a.png",
    "feedback": {
        "like": "7",
        "coin": "2",
        "star": "28",
        "share": "3"
    },
    "comments": [
        "表白封面玄雅小姐姐",
        "九缪斯大发",
        "青铜殿堂"
    ],
    "tags": [
        "娱乐",
        "明星",
        "Korea音乐舞蹈",
        ";9MUSES"
    ]
}