{
    "id": 3006056,
    "title": "【ZX_珞】Remember-Apink (舞蹈翻跳)之头发扎起来我就是少女:-)",
    "abstract": "自制  这次应该没人说我脸糊了吧。。粉红的舞我感觉不是很适合。。额，大家可以吐槽但不要人身攻击好么:-P  大家终于可以看清楚我的脸了( *︾▽︾) 让我想想下一作是怦然心动还是？~还有B站不知道怎么回事这次上传进度条一直都出错花了好久才算投上来。。希望下次不要在这样anti我了╮(╯﹏╰)╭（PS：感觉封面和我本人一个样子应该不会有人被封面骗进来我一直童叟无欺哈哈哈滚走╭(╯^╰)╮）",
    "authorId": 8928728,
    "uploadTime": 1443964694.0,
    "playCount": 5072,
    "commentCount": 14,
    "bulletCommentCount": 61,
    "imageUrl": "http://i0.hdslb.com/bfs/archive/543fd84362698f491cf0de644d5ced8acb528426.jpg",
    "feedback": {
        "like": "15",
        "coin": "30",
        "star": "57",
        "share": "5"
    },
    "comments": [
        "啊粉的小清新真是棒呆(°∀°)ﾉ驾驭的极强",
        "黄金殿堂",
        "期待室外呀妹子！腿很赞～加油！！",
        "不错哟～～～～～",
        "不错！！"
    ],
    "tags": [
        "韩舞",
        "翻跳",
        "明星舞蹈",
        "舞蹈",
        "明星舞蹈",
        "舞蹈",
        "萌妹子",
        "APNK"
    ]
}