{
    "id": 50008220,
    "title": "【邓伦×杨紫】【北奥夫妇】哪吒传奇？凤凰传奇？是他是他就是他~我们的朋友~小…凤凰？！哪吒？！",
    "abstract": "-",
    "authorId": 375906314,
    "uploadTime": 1555816972.0,
    "playCount": 1761,
    "commentCount": 3,
    "bulletCommentCount": 6,
    "imageUrl": "http://i0.hdslb.com/bfs/archive/f46e83b25cf229d77ee342786a679a90fa963824.jpg",
    "feedback": {
        "like": "45",
        "coin": "3",
        "star": "14",
        "share": "1"
    },
    "comments": [
        "忍不住跟着唱了起来",
        "哈哈哈哈哈哈哈哈哈哈哈哈哈哈哈哈哈哈哈哈哈哈哈哈哈哈哈哈哈哈哈哈哈哈哈哈哈哈哈哈哈哈哈哈哈哈哈哈哈哈哈哈哈哈哈哈哈xswl",
        "高级搬运工"
    ],
    "tags": [
        "邓伦",
        "杨紫",
        "搞笑",
        "娱乐",
        "明星",
        "明星",
        "CP",
        "混剪",
        "密室大逃脱"
    ]
}