{
    "id": 50008175,
    "title": "【绝地求生】Wadu也重回绝地求生！——Wadu拿M416+M24在雨林图吃鸡！【720P60帧】",
    "abstract": "https://www.youtube.com/watch?v=GPmVtEGSIe4\nYouTube作者：Squad Arena\n\n原标题：Wadu Hek - PUBG Solo - M416+M24 - Sanhok - April 2019",
    "authorId": 243847858,
    "uploadTime": 1555988439.0,
    "playCount": 259,
    "commentCount": 0,
    "bulletCommentCount": 91,
    "imageUrl": "http://i1.hdslb.com/bfs/archive/367e8db81b7f1fc25ae8bc8be13f0a6a2f38b680.png",
    "feedback": {
        "like": "9",
        "coin": "4",
        "star": "4",
        "share": "0"
    },
    "comments": [],
    "tags": [
        "绝地求生",
        "游戏",
        "网络游戏",
        "游戏视频",
        "网络游戏",
        "第一视角",
        "大逃杀",
        "绝地求生大逃杀",
        "PUBG",
        "WADU"
    ]
}