{
    "id": 5005315,
    "title": "【排骨】流光·雾中萤（天谕流光官方广播剧主题曲试听，将收录于排骨原创专辑《非月》中）",
    "abstract": "关注排骨的微博@排骨教主\n神魔双生如影，一念天堂，一念地狱，生死之间，流光斑驳迷离。——网易天谕流光官方广播剧主题曲，庆祝天谕619一周年！\n策划：红衣\n作曲/编曲：石一十一\n作词：十二月\n演唱：排骨教主\n混音：Mr.鱼\n此版本为试听版，无损版请购买排骨专辑",
    "authorId": 486183,
    "uploadTime": 1466177881.0,
    "playCount": 298526,
    "commentCount": 3435,
    "bulletCommentCount": 5736,
    "imageUrl": "http://i1.hdslb.com/bfs/archive/04ac7be15debc42b861a74e559099c51dd5a97d5.jpg",
    "feedback": {
        "like": "447",
        "coin": "1.3万",
        "star": "1.0万",
        "share": "1597"
    },
    "comments": [
        "深夜党的胜利",
        "排骨现在真是越来越气质了，感觉自己越来越爱不起了XXX失踪人口回归真是cao开心啊啊，发的新歌超好听的！特别期待新专辑《非月》发售！但是也心疼女神啊，搬微博：排骨教主+关注排骨教主  6月14日 19:26 来自 iPhone SE专辑最新消息，带有戏曲元素的那首歌被命名为《红妆》，男女合唱。今天在录这首歌，调定高了……嗓子哑了……制作方正在积极补救，敬请期待[笑cry]好心疼啊啊，女神一定不要累到自己要注意身体，多喝热水(苦笑)嗯。。然后撸个这首歌的简评。开始低低吟唱的男声，真的好棒，轻轻浅浅的像是在叙述着一个久远的故事。画面中进入一个黑衣男子，走到一位趴在血泊中的女子旁，缓缓地抚摸着她的脸庞，让人想入非非，一下子便进入了有些悲伤的气氛中。歌曲的调子突变，进入了带着些许起伏的调子。又是缓缓的趋于平静（女神太苏了XX），开着低音炮的排骨再次出现，缓缓叙述，平静的讲述。。。画风突变，歌曲也进入***部分，排骨用高音说着自己的洒脱，终于被释放的洒脱。啊啊，听的我真是心尖微颤。女神是最棒der",
        "“排骨诈尸了！！快给我把棺盖按住。”“你女神你还不放他出来？！”“按紧了，给我抬回家去！”（排骨：QAQ我没有诈尸啊！！）",
        "青铜殿堂",
        "1楼啊啊啊啊啊"
    ],
    "tags": [
        "天谕",
        "原创歌曲",
        "音乐",
        "原创音乐",
        "排骨女神",
        "排骨教主",
        "失踪人口回归",
        "流光·雾中萤",
        "流光",
        "要弯",
        "低音美哭",
        "专辑试听",
        "排骨",
        "终于等到你",
        "非月"
    ]
}