{
    "id": 70007231,
    "title": "【电影盘点】那些神操作的电影片段（第二十六弹）",
    "abstract": "<第九区>、<夺金三王>、<登陆之日>。\n上一期视频传送门:av69995035\nUP主的频道已经将视频分类好了，小伙伴们可以前去观看自己喜欢的视频哦！",
    "authorId": 431112130,
    "uploadTime": 1570164879.0,
    "playCount": 108,
    "commentCount": 1,
    "bulletCommentCount": 0,
    "imageUrl": "http://i0.hdslb.com/bfs/archive/a9d6c6a4688b80213b2e8eb9a957d6c6c6c1925e.jpg",
    "feedback": {
        "like": "5",
        "coin": "2",
        "star": "2",
        "share": "0"
    },
    "comments": [
        "三连"
    ],
    "tags": [
        "影视混剪",
        "影视剪辑",
        "影视",
        "影视剪辑",
        "经典",
        "电影",
        "混剪",
        "电影盘点",
        "登陆之日",
        "第九区",
        "夺金三王"
    ]
}