{
    "id": 90007719,
    "title": "趣味学围棋3",
    "abstract": "怪可爱",
    "authorId": 482431833,
    "uploadTime": 1582049146.0,
    "playCount": 190,
    "commentCount": 4,
    "bulletCommentCount": 4,
    "imageUrl": "http://i1.hdslb.com/bfs/archive/1027285e5ce312756a8eec0e2db1ea8a3d847834.jpg",
    "feedback": {
        "like": "7",
        "coin": "4",
        "star": "2",
        "share": "4"
    },
    "comments": [
        "好看",
        "",
        "青铜殿堂"
    ],
    "tags": [
        "围棋",
        "生活",
        "日常"
    ]
}