{
    "id": 90008434,
    "title": "少儿英语SE 01",
    "abstract": "",
    "authorId": 92744337,
    "uploadTime": 1582051127.0,
    "playCount": 65,
    "commentCount": 0,
    "bulletCommentCount": 0,
    "imageUrl": "http://i1.hdslb.com/bfs/archive/58edfb48d045c2051f564cab3246ea2e1dc3d013.jpg",
    "feedback": {
        "like": "0",
        "coin": "0",
        "star": "0",
        "share": "1"
    },
    "comments": [],
    "tags": [
        "短片",
        "影视",
        "短片",
        "课程",
        "学习",
        "少儿英语"
    ]
}