{
    "id": 90007980,
    "title": "2020年-前端架构师",
    "abstract": "",
    "authorId": 364798139,
    "uploadTime": 1582047735.0,
    "playCount": 17019,
    "commentCount": 22,
    "bulletCommentCount": 33,
    "imageUrl": "http://i2.hdslb.com/bfs/archive/e839a74eaca59f906be3f285817b751199716ce8.jpg",
    "feedback": {
        "like": "87",
        "coin": "47",
        "star": "980",
        "share": "30"
    },
    "comments": [
        "老哥有没有网盘 没网的时候没办法看",
        "牛逼",
        "毫无声音",
        "这个视频在网上找了，也下载了，最后需要解压密码，可惜没解压密码",
        "UP主，有没有配套的资料包，课件+代码"
    ],
    "tags": [
        "知识",
        "野生技能协会",
        "学习",
        "JAVASCRIPT",
        "前端",
        "JS",
        "NODEJS",
        "前端开发",
        "vue",
        "WEB前端",
        "架构师",
        "全栈工程师"
    ]
}