{
    "id": 90007765,
    "title": "分享一波真车短卡驾驶动态，因为拍的太好了。",
    "abstract": "https://www.youtube.com/watch?v=wGT2G6aiQ64",
    "authorId": 484984863,
    "uploadTime": 1582050429.0,
    "playCount": 31235,
    "commentCount": 80,
    "bulletCommentCount": 225,
    "imageUrl": "http://i2.hdslb.com/bfs/archive/09bdc031010c4a51db5a7c80847de48a2f678ab8.jpg",
    "feedback": {
        "like": "650",
        "coin": "102",
        "star": "880",
        "share": "257"
    },
    "comments": [
        "白银殿堂",
        "见习搬运工",
        "有这个悬挂我也可以送豆腐了",
        "饭圈楷模",
        "收集萌新"
    ],
    "tags": [
        "汽车",
        "汽车",
        "汽车生活",
        "越野",
        "红牛",
        "短卡"
    ]
}