{
    "id": 90007869,
    "title": "【原创妆面】七宗罪系列——Gluttony·色欲",
    "abstract": "出镜：朵朵\n摄影：阿朽、康康、朵朵\n后期：阿朽\n开了个新坑，年前录的视频年后拖了好久才剪出来的hhh\n喜欢请给个硬币点个赞！\nBGM：Infrared——Jordan Corey\nGrind Me Down——Jawster",
    "authorId": 21835598,
    "uploadTime": 1582079432.0,
    "playCount": 300,
    "commentCount": 9,
    "bulletCommentCount": 1,
    "imageUrl": "http://i0.hdslb.com/bfs/archive/6fabb7dc396b79c3ccf7f2cf34f3f013234b6832.jpg",
    "feedback": {
        "like": "21",
        "coin": "19",
        "star": "9",
        "share": "5"
    },
    "comments": [
        "大会员2018年度勋章",
        "wdm只有我一个人觉得有些角度像yyqx吗！！",
        "姐姐好可以",
        "首页通知书",
        "！！！三连了！！！"
    ],
    "tags": [
        "LOLITA FASHION",
        "彩妆",
        "美妆",
        "时尚",
        "美妆",
        "化妆",
        "Lolita"
    ]
}