{
    "id": 90007570,
    "title": "【过去那些事儿】第一弹:妈妈举报了叔叔偷粮",
    "abstract": "70年，家里没粮食，妈妈举报了去生产队偷粮食的叔叔",
    "authorId": 508393202,
    "uploadTime": 1582049475.0,
    "playCount": 16,
    "commentCount": 0,
    "bulletCommentCount": 0,
    "imageUrl": "http://i1.hdslb.com/bfs/archive/1a3c1414b21c31f2561bea6306e2158259860895.jpg",
    "feedback": {
        "like": "0",
        "coin": "0",
        "star": "0",
        "share": "0"
    },
    "comments": [],
    "tags": [
        "生活",
        "日常",
        "自制",
        "生活记录",
        "妈妈"
    ]
}