{
    "id": 10007855,
    "title": "【鹿晗】【陈长生】《择天记》cut8",
    "abstract": "《择天记》鹿晗cut",
    "authorId": 13982864,
    "uploadTime": 1492830784.0,
    "playCount": 3853,
    "commentCount": 2,
    "bulletCommentCount": 42,
    "imageUrl": "http://i1.hdslb.com/bfs/archive/44ac0cbc910069368c4bf1f0c10b4423d3382db8.jpg",
    "feedback": {
        "like": "31",
        "coin": "4",
        "star": "65",
        "share": "70"
    },
    "comments": [
        "饭圈萌新",
        "偏偏美少年"
    ],
    "tags": [
        "择天记",
        "鹿晗",
        "影视",
        "影视剪辑",
        "剪辑",
        "古装",
        "陈长生"
    ]
}