{
    "id": 1006309,
    "title": "PC「机动战士高达OL」DX Vol.11 机体介绍",
    "abstract": "「機動戦士ガンダムオンライン」DXガシャコン Vol.11紹介youtube.com/watch?v=Wh1evc5jtAw (搬运)",
    "authorId": 136001,
    "uploadTime": 1394607881.0,
    "playCount": 2548,
    "commentCount": 1,
    "bulletCommentCount": 12,
    "imageUrl": "http://i2.hdslb.com/bfs/archive/db599d6649467518ca4837b80846899104bd3ae3.jpg",
    "feedback": {
        "like": "2",
        "coin": "1",
        "star": "2",
        "share": "4"
    },
    "comments": [
        "差点以为是SD- -"
    ],
    "tags": [
        "游戏",
        "单机游戏",
        "机动戦士ガンダムオンライン",
        "预告资讯"
    ]
}