{
    "id": 20003405,
    "title": "【MMD刀剑乱舞】上弦之月【源氏兄弟】",
    "abstract": "续作：av20557445  前作：av19410782\n\n自制。有几位同好们近期（不约而同？）私信我，希望我能多做他俩同台的MMD。\n首先谢谢喜欢……其次，我的确是，疏忽了这点，经常条件反射玩单人solo（←太懒） 其他同好们对我的产出有啥建议的也可以私信我喔。\n至于这身衣服。\n之所以很少给他们穿这身，一是因为这衣服意义比较特殊（不过不必太在意），二是这穿起模来就没完没了了（再加上个扇子就更emmm）。本咸鱼尽力了，诸位包涵一下。\n借物在片末。\nBgm-上弦の月",
    "authorId": 7167497,
    "uploadTime": 1519473955.0,
    "playCount": 8293,
    "commentCount": 51,
    "bulletCommentCount": 44,
    "imageUrl": "http://i0.hdslb.com/bfs/archive/9c6a2ebc038de6e1c6f0bd7a27308d3932d813ad.jpg",
    "feedback": {
        "like": "210",
        "coin": "154",
        "star": "658",
        "share": "36"
    },
    "comments": [
        "弟弟丸：严肃又认真的一边唱歌一边跳舞哥哥切：不要太过紧张嘛歌丸，我不会因为弟弟先唱歌就压切弟弟的",
        "收集萌新",
        "啊不行这套衣服！！我吹爆！！",
        "阿尼甲好撩啊啊啊啊",
        "神仙渲染！膝ball他怎么这么好看prpr"
    ],
    "tags": [
        "动画",
        "MMD·3D",
        "膝丸",
        "髭切",
        "源氏兄弟"
    ]
}