{
    "id": 20003768,
    "title": "Kinu | 日杂LARME风粉色少女系妆容分享♡",
    "abstract": "https://weibo.com/tv/v/G4AlEpGc4?fid=1034:488201267cfd7f4bb52fd7b2e36772a1\n转自微博@就要日系搭\n\n希望大家多多投币给予我搬运更多的动力~",
    "authorId": 11004829,
    "uploadTime": 1519474335.0,
    "playCount": 1516,
    "commentCount": 7,
    "bulletCommentCount": 1,
    "imageUrl": "http://i0.hdslb.com/bfs/archive/3970c8de0a7fba372ac2bf38cda8cec9e0a9c28f.jpg",
    "feedback": {
        "like": "7",
        "coin": "2",
        "star": "56",
        "share": "7"
    },
    "comments": [
        "真的很奇怪，日本妹子明明天天化妆，怎么技术还是那么差",
        "认真的？",
        "排队！",
        "小姐姐这个眉毛画得，真让我着急，长得好看就是任性(▔□▔)/",
        "第一～"
    ],
    "tags": [
        "日常妆",
        "化妆品",
        "化妆教程",
        "彩妆",
        "美妆",
        "时尚",
        "美妆",
        "化妆",
        "分享",
        "妆容",
        "化妆技巧",
        "产品"
    ]
}