{
    "id": 30008263,
    "title": "炉石传说 砰砰计划冒险 斩杀",
    "abstract": "新人up主，求硬币，求点赞，求关注。素质三连",
    "authorId": 25583268,
    "uploadTime": 1534922503.0,
    "playCount": 27,
    "commentCount": 0,
    "bulletCommentCount": 0,
    "imageUrl": "http://i1.hdslb.com/bfs/archive/7fd6dbe52ba5910317dd35f3101771b2e9eb18b7.png",
    "feedback": {
        "like": "1",
        "coin": "0",
        "star": "0",
        "share": "6"
    },
    "comments": [],
    "tags": [
        "炉石传说",
        "卡牌游戏",
        "桌游棋牌",
        "游戏",
        "电子竞技",
        "电子竞技",
        "炉石"
    ]
}