{
    "id": 3006390,
    "title": "彗星硅舰队日常---一场出色的快攻",
    "abstract": "自制 打得比较拼的一场（其实差点玩脱(*/ω╲*)）\n刚开始经济差点崩掉，不过还好又恢复正常。之后试着rush对面那家黑章鱼，差点悲剧。\n后面依靠保护者（长得像乌贼的那些潜艇）强行碾压对手⊙▽⊙\n依旧欢迎各位观众在下方评论区留言提意见~",
    "authorId": 825363,
    "uploadTime": 1443967151.0,
    "playCount": 262,
    "commentCount": 0,
    "bulletCommentCount": 9,
    "imageUrl": "http://i0.hdslb.com/bfs/archive/d1a5a494a9e1367e8d7f6ec305e4745bfe82db8a.jpg",
    "feedback": {
        "like": "1",
        "coin": "1",
        "star": "1",
        "share": "11"
    },
    "comments": [],
    "tags": [
        "游戏",
        "单机游戏",
        "实况",
        "人机",
        "深海争霸"
    ]
}