{
    "id": 3006173,
    "title": " 【猫鱼实况】 【剧情向恐怖解谜】幻想少女糖果屋 P4",
    "abstract": "自制 woc这还有二周目???我感觉我的手残要经受考验了!!!",
    "authorId": 719036,
    "uploadTime": 1443965632.0,
    "playCount": 342,
    "commentCount": 27,
    "bulletCommentCount": 17,
    "imageUrl": "http://i2.hdslb.com/bfs/archive/926b078e055cca5535fe5f5a9dbdc6a95e722a99.jpg",
    "feedback": {
        "like": "0",
        "coin": "8",
        "star": "3",
        "share": "6"
    },
    "comments": [
        "喵鱼辛苦了~~~高产的猫鱼~~ε=ε=(ノ≧∇≦)ノ",
        "饭圈楷模",
        "（￣▽￣）",
        "饭圈大佬",
        "饭圈大佬"
    ],
    "tags": [
        "游戏",
        "单机游戏",
        "猫鱼",
        "幻想少女糖果屋"
    ]
}