{
    "id": 50007660,
    "title": "2019年‖第一支Vlog‖逛田地‖摘草莓‖遇见香味扑鼻的花",
    "abstract": "自己摘的草莓，更加美味。",
    "authorId": 9835298,
    "uploadTime": 1555817778.0,
    "playCount": 27,
    "commentCount": 0,
    "bulletCommentCount": 0,
    "imageUrl": "http://i1.hdslb.com/bfs/archive/9e434ea85facb1c3b22a5a30293fe3723dc0d931.jpg",
    "feedback": {
        "like": "1",
        "coin": "0",
        "star": "0",
        "share": "0"
    },
    "comments": [],
    "tags": [
        "vlog",
        "生活",
        "日常",
        "Vlog人生第一次",
        "草莓",
        "生活",
        "自制",
        "生活记录",
        "VLOG"
    ]
}