{
    "id": 50007605,
    "title": "Jim Newman's Family——Daddyhunt(老爹狩猎季又名攻略老爹)中的大叔演员(饰演Graydon)现实生活的二三事——爹地罗曼史",
    "abstract": "https://youtu.be/ColPSK4FBDg\nJim Newman's Family",
    "authorId": 309254608,
    "uploadTime": 1555833912.0,
    "playCount": 171,
    "commentCount": 1,
    "bulletCommentCount": 0,
    "imageUrl": "http://i2.hdslb.com/bfs/archive/220c5ff40674df3b9b4e733087cfb051154bb4c1.jpg",
    "feedback": {
        "like": "7",
        "coin": "1",
        "star": "3",
        "share": "0"
    },
    "comments": [
        "收集达人"
    ],
    "tags": [
        "生活",
        "日常",
        "大叔",
        "生活记录",
        "帅哥",
        "同志",
        "性感",
        "男神"
    ]
}