{
    "id": 50007540,
    "title": "九郎式rap吗",
    "abstract": "-",
    "authorId": 260504603,
    "uploadTime": 1555816087.0,
    "playCount": 99,
    "commentCount": 1,
    "bulletCommentCount": 0,
    "imageUrl": "http://i1.hdslb.com/bfs/archive/54f7e2d602f87e6a6d858862174d62d1756dc9fe.jpg",
    "feedback": {
        "like": "6",
        "coin": "0",
        "star": "0",
        "share": "0"
    },
    "comments": [
        "难不倒我九郎"
    ],
    "tags": [
        "杨九郎",
        "综艺",
        "搞笑",
        "娱乐",
        "综艺",
        "德云社",
        "娱乐",
        "张云雷杨九郎",
        "九辫"
    ]
}