{
    "id": 50008263,
    "title": "狼人大战吸血鬼，最后开始生存",
    "abstract": "我又回来了",
    "authorId": 357897782,
    "uploadTime": 1555817773.0,
    "playCount": 85,
    "commentCount": 0,
    "bulletCommentCount": 0,
    "imageUrl": "http://i1.hdslb.com/bfs/archive/44ab139422af51e6c4725f49a8696206ad9318b5.jpg",
    "feedback": {
        "like": "4",
        "coin": "0",
        "star": "0",
        "share": "0"
    },
    "comments": [],
    "tags": [
        "我的世界",
        "游戏",
        "手机游戏",
        "手机游戏",
        "游戏视频",
        "实况"
    ]
}