{
    "id": 50007832,
    "title": "NBAlive（第三期）休斯顿火箭vs金州勇士",
    "abstract": "请大家支持我的投稿，我会搞动漫，游戏和生活周边的生活视频，情多多关照，谢谢！",
    "authorId": 143438094,
    "uploadTime": 1555816932.0,
    "playCount": 165,
    "commentCount": 1,
    "bulletCommentCount": 0,
    "imageUrl": "http://i0.hdslb.com/bfs/archive/f6af82e90da6129a99b1a38698508370e05cdcdc.jpg",
    "feedback": {
        "like": "3",
        "coin": "2",
        "star": "1",
        "share": "0"
    },
    "comments": [
        "青铜殿堂"
    ],
    "tags": [
        "篮球",
        "单机游戏",
        "游戏",
        "手机游戏",
        "手机游戏",
        "手游",
        "NBA",
        "NBALIVE"
    ]
}