{
    "id": 70007550,
    "title": "主播油条直播录像2019-10-04 8时58分--10时24分 油条：AP蛮子走一走啊！哈哈哈",
    "abstract": "http://www.douyu.com/56040\n本录制组提供直播录制服务（录制指定主播，支持所有平台）| 提供更多历史视频网盘合集(2015年录制至今) | 请私聊联系本录制组",
    "authorId": 335435032,
    "uploadTime": 1570166482.0,
    "playCount": 121,
    "commentCount": 0,
    "bulletCommentCount": 0,
    "imageUrl": "http://i2.hdslb.com/bfs/archive/c507ac9a85eff9c3098ede0b64772d0078ef4c4a.jpg",
    "feedback": {
        "like": "1",
        "coin": "0",
        "star": "0",
        "share": "0"
    },
    "comments": [],
    "tags": [
        "游戏",
        "电子竞技",
        "电子竞技",
        "直播",
        "录播",
        "录制",
        "主播",
        "录像",
        "重播",
        "回放"
    ]
}