{
    "id": 70007309,
    "title": "【桃李面包合辑】 鸡蛋香松面包 雪双心草莓奶酪味面包 日式三明治口袋面包 菠萝面包 起酥面包 明治牛奶泡卡乐比",
    "abstract": "多多关注、评论、弹幕哦~\n有机会的话给大家浮力~",
    "authorId": 180359830,
    "uploadTime": 1570164676.0,
    "playCount": 883,
    "commentCount": 6,
    "bulletCommentCount": 1,
    "imageUrl": "http://i1.hdslb.com/bfs/archive/6ac3e7dfc9074d371c0efd8e8e2aac389478d38e.jpg",
    "feedback": {
        "like": "8",
        "coin": "2",
        "star": "1",
        "share": "0"
    },
    "comments": [
        "第一条评论 我爱桃李 不过up吃的好多种我都没在学校超市见过 坐标成都",
        "啊！爱好重叠！"
    ],
    "tags": [
        "试吃",
        "甜点",
        "烘焙",
        "美食侦探",
        "吃货",
        "美食",
        "美食",
        "美食侦探",
        "假期美味分享",
        "自制",
        "美食圈",
        "生活"
    ]
}