{
    "id": 70007395,
    "title": "想养宠物，但是又害怕宠物是生病的！我们应该如何去检查？",
    "abstract": "#经验分享##创作新秀奖#\n害怕买到的生病的宠物？不用害怕，我来教你！\n书面的“售卖协议”是可以极大的保障你购买时的权益，一般对自己所售卖宠物有信心的卖家，都会很乐意签写“售卖协议”。",
    "authorId": 12398229,
    "uploadTime": 1570164308.0,
    "playCount": 94,
    "commentCount": 1,
    "bulletCommentCount": 0,
    "imageUrl": "http://i1.hdslb.com/bfs/archive/14421702ab48dce0883e260482d488e78d84f092.png",
    "feedback": {
        "like": "8",
        "coin": "8",
        "star": "5",
        "share": "0"
    },
    "comments": [
        "第三课"
    ],
    "tags": [
        "萌宠",
        "动物圈",
        "喵星人",
        "铲屎官",
        "日常",
        "原创",
        "猫",
        "动物圈",
        "经验分享",
        "生病",
        "狗",
        "宠物",
        "主人"
    ]
}