{
    "id": 8007940,
    "title": "【一拳超人MMD 】Tokio Funka Ft Saitama (HAPPY NEW YEAR!)",
    "abstract": "http://www.nicovideo.jp/watch/sm30349091 CheeseVe さん((Saitama by モドキ))((Motion))((Thank you for the models,stage,effects and motion.))\n浴衣老师和不经意露出的（哔——）真是太棒了，可惜源就很渣画质，十分抱歉，一旦有更高清的会立即更换。 ​​​​",
    "authorId": 755087,
    "uploadTime": 1484390781.0,
    "playCount": 646,
    "commentCount": 12,
    "bulletCommentCount": 21,
    "imageUrl": "http://i1.hdslb.com/bfs/archive/2ed47c58a27460707965d8f2aa9cc8f67882ebe2.jpg",
    "feedback": {
        "like": "6",
        "coin": "7",
        "star": "37",
        "share": "4"
    },
    "comments": [
        "浴衣老师prprprpr",
        "大过年的突然看到老师认真跳舞！",
        "好棒呀老师好妖娆啊啊啊啊啊(´；ω；`)",
        "饭圈萌新",
        "能把BGM的名字告诉吾辈吗！！"
    ],
    "tags": [
        "MMD",
        "动画",
        "MMD·3D",
        "MMD.3D",
        "一拳超人",
        "埼玉老师",
        "一拳超人MMD"
    ]
}