{
    "id": 8007361,
    "title": "柊泠電繪~人設繪第一篇 膚色篇~<3",
    "abstract": "這是柊泠第一次上傳影片\n在後製中遇到了很多障礙呀...\n影片希望各位喜歡~\n頻道歡迎支持~\n\n使用的繪圖軟體是\nMediBang Paint Pro",
    "authorId": 27213386,
    "uploadTime": 1484388873.0,
    "playCount": 87,
    "commentCount": 0,
    "bulletCommentCount": 0,
    "imageUrl": "http://i2.hdslb.com/bfs/archive/7e37ffc738aa4a898384f350bf442ae1555bbaaf.jpg",
    "feedback": {
        "like": "0",
        "coin": "0",
        "star": "1",
        "share": "4"
    },
    "comments": [],
    "tags": [
        "生活",
        "绘画",
        "新人",
        "電繪過程"
    ]
}