{
    "id": 8007572,
    "title": "Top Vines of Meghan McCarthy (w_Titles) Meghan McCarthy Vine Compilation",
    "abstract": "youtube Top Vines of Meghan McCarthy (w/Titles) Meghan McCarthy Vine Compilation - Co Vines✔\nhttps://www.youtube.com/watch?v=PvKCrZfQVpg&amp;t=171s",
    "authorId": 22375764,
    "uploadTime": 1484389484.0,
    "playCount": 253,
    "commentCount": 0,
    "bulletCommentCount": 0,
    "imageUrl": "http://i0.hdslb.com/bfs/archive/4bd7ebbda5aa32676735f1935dc3903f7ea239b6.jpg",
    "feedback": {
        "like": "0",
        "coin": "0",
        "star": "11",
        "share": "4"
    },
    "comments": [],
    "tags": [
        "生活",
        "搞笑",
        "YouTube搬运"
    ]
}