{
    "id": 90008439,
    "title": "东北安琪拉在线扭秧歌",
    "abstract": "-",
    "authorId": 17298529,
    "uploadTime": 1582049643.0,
    "playCount": 28,
    "commentCount": 1,
    "bulletCommentCount": 0,
    "imageUrl": "http://i1.hdslb.com/bfs/archive/59d9f273bbb0fa1f8e269d4457d098a87b789b07.jpg",
    "feedback": {
        "like": "1",
        "coin": "0",
        "star": "0",
        "share": "0"
    },
    "comments": [
        "你这，勉强一个赞吧"
    ],
    "tags": [
        "王者荣耀",
        "游戏",
        "手机游戏",
        "手机游戏",
        "王者农药",
        "安琪拉",
        "王者荣耀搞笑视频",
        "bilibili新星计划"
    ]
}