{
    "id": 90007860,
    "title": "从此以后不在分开，一起猪突猛进吧!",
    "abstract": "猪突猛进，猪突猛进，\nBGM:别认怂",
    "authorId": 94899839,
    "uploadTime": 1582049829.0,
    "playCount": 32,
    "commentCount": 0,
    "bulletCommentCount": 0,
    "imageUrl": "http://i0.hdslb.com/bfs/archive/5d8dfc32bb6f5b76eb30e1588f0cd284ae79e52f.jpg",
    "feedback": {
        "like": "5",
        "coin": "4",
        "star": "1",
        "share": "2"
    },
    "comments": [],
    "tags": [
        "鬼灭之刃",
        "动画",
        "综合",
        "bilibili新星计划"
    ]
}