{
    "id": 90007623,
    "title": "亮亮的快乐雀魂 第一期",
    "abstract": "群号592839575，欢迎大家来玩耍，直播面向所有段位，希望大家都会有收获。",
    "authorId": 13693484,
    "uploadTime": 1582051806.0,
    "playCount": 68,
    "commentCount": 2,
    "bulletCommentCount": 0,
    "imageUrl": "http://i1.hdslb.com/bfs/archive/0d02fe42b50c2a4887bd48e621ad6c2c188704b9.jpg",
    "feedback": {
        "like": "1",
        "coin": "2",
        "star": "0",
        "share": "0"
    },
    "comments": [
        "约瑟夫",
        "大会员2018年度勋章"
    ],
    "tags": [
        "日麻",
        "雀魂",
        "桌游棋牌",
        "游戏",
        "桌游棋牌",
        "日本麻将"
    ]
}