{
    "id": 90007908,
    "title": "寻死与送葬。",
    "abstract": "音乐：小曲儿 - 霜华浓\n素材：取自贴吧吧友分享\n杀犬短篇《寻死与送葬》伪后续。\n2020年12月18日\n掌中烛火。",
    "authorId": 99446644,
    "uploadTime": 1582051101.0,
    "playCount": 570,
    "commentCount": 4,
    "bulletCommentCount": 0,
    "imageUrl": "http://i0.hdslb.com/bfs/archive/29ac23c42ba366904b2a750f1c974db5a546f1fb.jpg",
    "feedback": {
        "like": "17",
        "coin": "9",
        "star": "13",
        "share": "0"
    },
    "comments": [
        "太太真的高产！！！可是好虐π_π，看完又去补文的我要出不去了(ﾉಥ益ಥ)，感觉大狗在亲手杀了二狗之后就一直在思考自己这样做到底值不值得但又已经无法挽回，只能不断回忆和二狗有关的过去度过余生，真的好虐啊",
        "简介亮了",
        "太太好高产！嗷呜"
    ],
    "tags": [
        "杀生丸",
        "犬夜叉",
        "影视",
        "影视剪辑",
        "杀犬"
    ]
}