{
    "id": 90007754,
    "title": "EXO三代应援棒测试视频，尝试了中控，很美！",
    "abstract": "三代爱丽棒很漂亮，可中控，用中控软件后的颜色太美了，惊呆我了！",
    "authorId": 337231275,
    "uploadTime": 1582049706.0,
    "playCount": 278,
    "commentCount": 0,
    "bulletCommentCount": 0,
    "imageUrl": "http://i0.hdslb.com/bfs/archive/ae6d414a20608f010f4b4f19bb7743d5b08df6a6.jpg",
    "feedback": {
        "like": "1",
        "coin": "0",
        "star": "0",
        "share": "0"
    },
    "comments": [],
    "tags": [
        "EXO",
        "娱乐",
        "明星",
        "明星",
        "音乐",
        "周边",
        "应援",
        "EXOL",
        "KOKOBOP"
    ]
}