{
    "id": 90007296,
    "title": "【Manta翻唱】刘柏辛，女声电音翻唱！！",
    "abstract": "-",
    "authorId": 335882365,
    "uploadTime": 1582049004.0,
    "playCount": 36,
    "commentCount": 0,
    "bulletCommentCount": 0,
    "imageUrl": "http://i1.hdslb.com/bfs/archive/df1ac04de3dea24bc52917c176e00cf0a9a13b97.jpg",
    "feedback": {
        "like": "2",
        "coin": "0",
        "star": "0",
        "share": "0"
    },
    "comments": [],
    "tags": [
        "电音",
        "翻唱",
        "音乐",
        "翻唱",
        "女声翻唱",
        "Manta",
        "刘柏辛"
    ]
}