{
    "id": 90007876,
    "title": "雅马哈YAMAHAMT-09/倒霉的19年最后一骑",
    "abstract": "https://m.youtube.com/watch?v=UWrccMRXHMg",
    "authorId": 49586400,
    "uploadTime": 1582050786.0,
    "playCount": 512,
    "commentCount": 0,
    "bulletCommentCount": 0,
    "imageUrl": "http://i2.hdslb.com/bfs/archive/4dbaa04a80f95ce3479d106f9b54cfca307dc013.jpg",
    "feedback": {
        "like": "5",
        "coin": "0",
        "star": "4",
        "share": "0"
    },
    "comments": [],
    "tags": [
        "摩托车",
        "日本",
        "汽车",
        "汽车",
        "汽车生活",
        "YAMAHA",
        "雅马哈"
    ]
}