{
    "id": 90007613,
    "title": "[Rust建家教程] 你们想要的UT家来了！",
    "abstract": "UT直播交流通知群：817108120",
    "authorId": 487382846,
    "uploadTime": 1582051605.0,
    "playCount": 49153,
    "commentCount": 88,
    "bulletCommentCount": 150,
    "imageUrl": "http://i0.hdslb.com/bfs/archive/ef3b637bd4716476bace5997dafe28e272aae90c.jpg",
    "feedback": {
        "like": "477",
        "coin": "311",
        "star": "1032",
        "share": "690"
    },
    "comments": [
        "3x3内部结构要自己想，这个视频只是教你们扩建",
        "低倍服用不到高倍服随便炸",
        "怎么防炸层吃不到领地柜",
        "饭圈萌新",
        "饭圈大佬"
    ],
    "tags": [
        "单机游戏",
        "游戏",
        "单机游戏",
        "生存游戏",
        "演示",
        "教程",
        "单机联机",
        "RUST腐蚀"
    ]
}